LICENSE
README.md
setup.py
PV_diagnosis/__init__.py
PV_diagnosis/main.py
PV_diagnosis.egg-info/PKG-INFO
PV_diagnosis.egg-info/SOURCES.txt
PV_diagnosis.egg-info/dependency_links.txt
PV_diagnosis.egg-info/requires.txt
PV_diagnosis.egg-info/top_level.txt